cspdk/__init__.py
cspdk/si220/__init__.py
cspdk/si220/cband/__init__.py
cspdk/si220/cband/config.py
cspdk/si220/cband/import_pdk.py
cspdk/si220/cband/layers.yaml
cspdk/si220/cband/tech.py
cspdk/si220/cband/cells/__init__.py
cspdk/si220/cband/cells/containers.py
cspdk/si220/cband/cells/couplers.py
cspdk/si220/cband/cells/die_with_pads.py
cspdk/si220/cband/cells/fixed.py
cspdk/si220/cband/cells/grating_couplers.py
cspdk/si220/cband/cells/heaters.py
cspdk/si220/cband/cells/mmis.py
cspdk/si220/cband/cells/mzis.py
cspdk/si220/cband/cells/rings.py
cspdk/si220/cband/cells/spirals.py
cspdk/si220/cband/cells/tapers.py
cspdk/si220/cband/cells/text.py
cspdk/si220/cband/cells/vias.py
cspdk/si220/cband/cells/waveguides.py
cspdk/si220/cband/gds/CORNERSTONE MPW SOI 220nm GDSII Template.gds
cspdk/si220/cband/gds/Cell0_Institution_Name.gds
cspdk/si220/cband/gds/Cell0_SOI220_Full_1550nm_Packaging_Template.gds
cspdk/si220/cband/gds/Cell0_SOI_Full_Institution_Name.gds
cspdk/si220/cband/gds/Cell0_SOI_Half_Institution_Name.gds
cspdk/si220/cband/gds/Flip_Chip_Bonding_Example.gds
cspdk/si220/cband/gds/Heater.gds
cspdk/si220/cband/gds/Layer_Designations.gds
cspdk/si220/cband/gds/SOI220nm_1310nm_TE_RIB_2x1_MMI.gds
cspdk/si220/cband/gds/SOI220nm_1310nm_TE_RIB_2x2_MMI.gds
cspdk/si220/cband/gds/SOI220nm_1310nm_TE_RIB_90_Degree_Bend.gds
cspdk/si220/cband/gds/SOI220nm_1310nm_TE_RIB_Grating_Coupler.gds
cspdk/si220/cband/gds/SOI220nm_1310nm_TE_RIB_Waveguide.gds
cspdk/si220/cband/gds/SOI220nm_1310nm_TE_RIB_Waveguide_Crossing.gds
cspdk/si220/cband/gds/SOI220nm_1310nm_TE_STRIP_2x1_MMI.gds
cspdk/si220/cband/gds/SOI220nm_1310nm_TE_STRIP_2x2_MMI.gds
cspdk/si220/cband/gds/SOI220nm_1310nm_TE_STRIP_90_Degree_Bend.gds
cspdk/si220/cband/gds/SOI220nm_1310nm_TE_STRIP_Grating_Coupler.gds
cspdk/si220/cband/gds/SOI220nm_1310nm_TE_STRIP_Waveguide.gds
cspdk/si220/cband/gds/SOI220nm_1310nm_TE_STRIP_Waveguide_Crossing.gds
cspdk/si220/cband/gds/SOI220nm_1550nm_TE_RIB_2x1_MMI.gds
cspdk-1.4.1.dist-info/licenses/LICENSE
cspdk-1.4.1.dist-info/WHEEL
cspdk-1.4.1.dist-info/METADATA
cspdk-1.4.1.dist-info/RECORD
