Metadata-Version: 2.4
Name: cspdk
Version: 1.4.1
Summary: CornerStone PDK
Keywords: python
Author-email: gdsfactory <contact@gdsfactory.com>
Requires-Python: >=3.11,<3.14
Classifier: Programming Language :: Python :: 3.11
Classifier: Programming Language :: Python :: 3.12
Classifier: Programming Language :: Python :: 3.13
Classifier: Operating System :: OS Independent
License-File: LICENSE
Requires-Dist: gdsfactory~=9.29.1
Requires-Dist: gplugins[sax, tidy3d]~=2.0.0
Requires-Dist: doroutes>=0.3.0
Requires-Dist: pre-commit ; extra == "dev"
Requires-Dist: jsondiff ; extra == "dev"
Requires-Dist: pytest ; extra == "dev"
Requires-Dist: pytest-cov ; extra == "dev"
Requires-Dist: pytest_regressions ; extra == "dev"
Requires-Dist: pytest-github-actions-annotate-failures ; extra == "dev"
Requires-Dist: gdsfactoryplus ; extra == "dev"
Requires-Dist: towncrier ; extra == "dev"
Requires-Dist: jupytext ; extra == "docs"
Requires-Dist: matplotlib ; extra == "docs"
Requires-Dist: jupyter-book>=0.15.1,<1.1 ; extra == "docs"
Provides-Extra: dev
Provides-Extra: docs
